python_telnet_vlc/__init__.py
python_telnet_vlc/vlctelnet.py
python_telnet_vlc-2.0.1.dist-info/LICENSE
python_telnet_vlc-2.0.1.dist-info/METADATA
python_telnet_vlc-2.0.1.dist-info/WHEEL
python_telnet_vlc-2.0.1.dist-info/top_level.txt
python_telnet_vlc-2.0.1.dist-info/RECORD
