Metadata-Version: 2.1
Name: python-telnet-vlc
Version: 2.0.1
Summary: A library to control or get information about VLC using Telnet
Home-page: https://github.com/rodripf/python-telnet-vlc
Author: stephenmac7, rodripf, BilliAlpha, David McClosky
Author-email: rodripf@gmail.com
License: UNKNOWN
Platform: UNKNOWN
Classifier: Programming Language :: Python :: 3
Classifier: License :: OSI Approved :: GNU General Public License v3 (GPLv3)
Classifier: Operating System :: OS Independent
Classifier: Development Status :: 4 - Beta
Classifier: Topic :: Multimedia
